trame/__init__.py
trame/modules/__init__.py
trame/modules/quasar.py
trame/ui/__init__.py
trame/ui/quasar.py
trame/widgets/__init__.py
trame/widgets/quasar.py
trame_quasar/__init__.py
trame_quasar/module/__init__.py
trame_quasar/module/quasar/__init__.py
trame_quasar/module/quasar/vue3.py
trame_quasar/module/quasar/vue3/1.js
trame_quasar/module/quasar/vue3/2.css
trame_quasar/module/quasar/vue3/KFOkCnqEu92Fr1MmgWxP.ttf
trame_quasar/module/quasar/vue3/KFOlCnqEu92Fr1MmEU9vAw.ttf
trame_quasar/module/quasar/vue3/KFOlCnqEu92Fr1MmSU5vAw.ttf
trame_quasar/module/quasar/vue3/KFOlCnqEu92Fr1MmWUlvAw.ttf
trame_quasar/module/quasar/vue3/KFOlCnqEu92Fr1MmYUtvAw.ttf
trame_quasar/module/quasar/vue3/KFOmCnqEu92Fr1Me5Q.ttf
trame_quasar/module/quasar/vue3/flUhRq6tzZclQEJ-Vdg-IuiaDsNZ.ttf
trame_quasar/module/quasar/vue3/fonts.css
trame_quasar/module/quasar/vue3/trame_utils.js
trame_quasar/ui/__init__.py
trame_quasar/ui/quasar.py
trame_quasar/widgets/__init__.py
trame_quasar/widgets/quasar.py
trame_quasar-0.2.1.dist-info/LICENSE
trame_quasar-0.2.1.dist-info/METADATA
trame_quasar-0.2.1.dist-info/WHEEL
trame_quasar-0.2.1.dist-info/top_level.txt
trame_quasar-0.2.1.dist-info/RECORD
